xtenors/__about__.py
xtenors/__init__.py
xtenors/adjustments.py
xtenors/arithmetic.py
xtenors/calendars.py
xtenors/conventions.py
xtenors/dates.py
xtenors/iterators.py
xtenors/units.py
xtenors/xtenors.py
xtenors-3.0.1.dist-info/METADATA
xtenors-3.0.1.dist-info/WHEEL
xtenors-3.0.1.dist-info/licenses/LICENSE
xtenors-3.0.1.dist-info/licenses/LICENSE.txt
xtenors-3.0.1.dist-info/RECORD
