Metadata-Version: 2.1
Name: xtenors
Version: 3.0.1
Project-URL: Documentation, https://tomjrwilliams.github.io/xtenors/
Project-URL: Issues, https://github.com/tomjrwilliams/xtenors/issues
Project-URL: Source, https://github.com/tomjrwilliams/xtenors
Author-email: Tom Williams <tomjrw@gmail.com>
License-Expression: MIT
License-File: LICENSE
License-File: LICENSE.txt
Classifier: Development Status :: 4 - Beta
Classifier: Programming Language :: Python
Classifier: Programming Language :: Python :: 3.9
Classifier: Programming Language :: Python :: Implementation :: CPython
Classifier: Programming Language :: Python :: Implementation :: PyPy
Requires-Python: ==3.9
Requires-Dist: cython
Requires-Dist: holidays
Requires-Dist: pandas
Requires-Dist: pandas-market-calendars
Requires-Dist: xtuples>=2.0.0
